setup.py
tex.py
tex.egg-info/PKG-INFO
tex.egg-info/SOURCES.txt
tex.egg-info/dependency_links.txt
tex.egg-info/top_level.txt