Metadata-Version: 1.1
Name: tex
Version: 1.8
Summary: Convert LaTeX or TeX source to PDF or DVI, and escape strings for LaTeX.
Home-page: http://www.profv.de/python-tex/
Author: Volker Grabsch
Author-email: vog@notjusthosting.com
License: UNKNOWN
Platform: UNKNOWN
Classifier: Development Status :: 5 - Production/Stable
Classifier: Development Status :: 6 - Mature
Classifier: Development Status :: 7 - Inactive
Classifier: Intended Audience :: Developers
Classifier: License :: OSI Approved :: MIT License
Classifier: Operating System :: OS Independent
Classifier: Programming Language :: Python
Classifier: Topic :: Documentation
Classifier: Topic :: Office/Business
Classifier: Topic :: Printing
Classifier: Topic :: Software Development :: Libraries :: Python Modules
Classifier: Topic :: Text Processing :: Markup :: LaTeX
